keepercommander/.gitignore
keepercommander/__init__.py
keepercommander/__main__.py
keepercommander/api.py
keepercommander/attachment.py
keepercommander/autocomplete.py
keepercommander/base32hex.py
keepercommander/breachwatch.py
keepercommander/cli.py
keepercommander/command_categories.py
keepercommander/constants.py
keepercommander/convert_keys.py
keepercommander/crypto.py
keepercommander/crypto.pyi
keepercommander/display.py
keepercommander/email_service.py
keepercommander/enforcement.py
keepercommander/enterprise.py
keepercommander/error.py
keepercommander/generator.py
keepercommander/loginv3.py
keepercommander/native.py
keepercommander/oauth_helpers.py
keepercommander/params.py
keepercommander/record.py
keepercommander/record_facades.py
keepercommander/record_management.py
keepercommander/record_types.py
keepercommander/recordv3.py
keepercommander/rest_api.py
keepercommander/security_audit.py
keepercommander/shared_folder.py
keepercommander/shared_record.py
keepercommander/subfolder.py
keepercommander/sync_down.py
keepercommander/team.py
keepercommander/ttk.py
keepercommander/utils.py
keepercommander/vault.py
keepercommander/vault_extensions.py
keepercommander/versioning.py
keepercommander/auth/__init__.py
keepercommander/auth/console_ui.py
keepercommander/auth/login_steps.py
keepercommander/biometric/README.md
keepercommander/biometric/__init__.py
keepercommander/biometric/client.py
keepercommander/biometric/commands/__init__.py
keepercommander/biometric/commands/base.py
keepercommander/biometric/commands/list.py
keepercommander/biometric/commands/register.py
keepercommander/biometric/commands/unregister.py
keepercommander/biometric/commands/update_name.py
keepercommander/biometric/commands/verify.py
keepercommander/biometric/platforms/__init__.py
keepercommander/biometric/platforms/base.py
keepercommander/biometric/platforms/detector.py
keepercommander/biometric/platforms/windows.py
keepercommander/biometric/platforms/macos/__init__.py
keepercommander-17.2.7.dist-info/licenses/LICENSE
keepercommander-17.2.7.dist-info/METADATA
keepercommander-17.2.7.dist-info/WHEEL
keepercommander-17.2.7.dist-info/entry_points.txt
keepercommander-17.2.7.dist-info/top_level.txt
keepercommander-17.2.7.dist-info/RECORD
