Metadata-Version: 2.4
Name: keepercommander
Version: 17.2.7
Summary: Keeper Commander for Python 3
Home-page: https://keepersecurity.com/
Download-URL: https://github.com/Keeper-Security/Commander/releases
Author: Craig Lurey
Author-email: craig@keepersecurity.com
License: MIT
Keywords: security,password
Classifier: Environment :: Console
Classifier: Development Status :: 4 - Beta
Classifier: License :: OSI Approved :: MIT License
Classifier: Operating System :: OS Independent
Classifier: Programming Language :: Python :: 3 :: Only
Classifier: Programming Language :: Python :: 3.7
Classifier: Topic :: Security
Requires-Python: >=3.7
License-File: LICENSE
Requires-Dist: asciitree
Requires-Dist: bcrypt
Requires-Dist: colorama
Requires-Dist: cryptography>=41.0.0
Requires-Dist: fido2>=2.0.0; python_version >= "3.10"
Requires-Dist: flask; python_version >= "3.8"
Requires-Dist: flask-limiter; python_version >= "3.8"
Requires-Dist: keeper-secrets-manager-core>=16.6.0
Requires-Dist: prompt_toolkit
Requires-Dist: protobuf>=4.23.0
Requires-Dist: psutil; python_version >= "3.8"
Requires-Dist: pycryptodomex>=3.20.0
Requires-Dist: pyngrok; python_version >= "3.8"
Requires-Dist: pyperclip
Requires-Dist: python-dotenv
Requires-Dist: requests>=2.31.0
Requires-Dist: tabulate
Requires-Dist: websockets
Requires-Dist: keeper_pam_webrtc_rs>=1.2.1; python_version >= "3.8"
Requires-Dist: pydantic>=2.6.4; python_version >= "3.8"
Requires-Dist: fpdf2>=2.8.3
Requires-Dist: cbor2; sys_platform == "darwin" and python_version >= "3.10"
Requires-Dist: pyobjc-framework-LocalAuthentication; sys_platform == "darwin" and python_version >= "3.10"
Requires-Dist: winrt-runtime; sys_platform == "win32" and python_version >= "3.10"
Requires-Dist: winrt-Windows.Foundation; sys_platform == "win32" and python_version >= "3.10"
Requires-Dist: winrt-Windows.Security.Credentials.UI; sys_platform == "win32" and python_version >= "3.10"
Requires-Dist: keeper-mlkem; python_version >= "3.11"
Requires-Dist: textual; python_version >= "3.9"
Provides-Extra: test
Requires-Dist: pytest; extra == "test"
Requires-Dist: testfixtures; extra == "test"
Provides-Extra: email-sendgrid
Requires-Dist: sendgrid>=6.10.0; extra == "email-sendgrid"
Provides-Extra: email-ses
Requires-Dist: boto3>=1.26.0; extra == "email-ses"
Provides-Extra: email-gmail-oauth
Requires-Dist: google-auth>=2.16.0; extra == "email-gmail-oauth"
Requires-Dist: google-auth-oauthlib>=0.8.0; extra == "email-gmail-oauth"
Requires-Dist: google-auth-httplib2>=0.1.0; extra == "email-gmail-oauth"
Requires-Dist: google-api-python-client>=2.70.0; extra == "email-gmail-oauth"
Provides-Extra: email-microsoft-oauth
Requires-Dist: msal>=1.20.0; extra == "email-microsoft-oauth"
Provides-Extra: email
Requires-Dist: sendgrid>=6.10.0; extra == "email"
Requires-Dist: boto3>=1.26.0; extra == "email"
Requires-Dist: google-auth>=2.16.0; extra == "email"
Requires-Dist: google-auth-oauthlib>=0.8.0; extra == "email"
Requires-Dist: google-auth-httplib2>=0.1.0; extra == "email"
Requires-Dist: google-api-python-client>=2.70.0; extra == "email"
Requires-Dist: msal>=1.20.0; extra == "email"
Dynamic: download-url
Dynamic: license-file
